percentile_rank/__init__.py
percentile_rank/rank.py
percentile_rank-1.0.4.dist-info/LICENSE
percentile_rank-1.0.4.dist-info/METADATA
percentile_rank-1.0.4.dist-info/WHEEL
percentile_rank-1.0.4.dist-info/top_level.txt
percentile_rank-1.0.4.dist-info/RECORD
