Metadata-Version: 2.1
Name: percentile-rank
Version: 1.0.4
Summary: Returns the percentile of a value. Returns the same values as the Excel PERCENTRANK and PERCENTRANK.INC functions.
Home-page: https://github.com/malcolmvr/percentile_rank
Download-URL: https://github.com/malcolmvr/percentile_rank/archive/v1.0.3.tar.gz
Author: Malcolm van Raalte
Author-email: malcolm@van.raalte.ca
License: MIT
Keywords: percentile,rank,percentrank,percentrank.inc,excel
Classifier: Development Status :: 5 - Production/Stable
Classifier: Topic :: Software Development :: Build Tools
Classifier: License :: OSI Approved :: MIT License
Classifier: Programming Language :: Python :: 3.3
Classifier: Programming Language :: Python :: 3.4
Classifier: Programming Language :: Python :: 3.5
Classifier: Programming Language :: Python :: 3.6
Classifier: Programming Language :: Python :: 3.7
Classifier: Programming Language :: Python :: 3.8
Classifier: Programming Language :: Python :: 3.9
Classifier: Programming Language :: Python :: 3.10
License-File: LICENSE
